MANIFEST.in
README.md
readme.md
setup.py
gen_name_szczep.egg-info/PKG-INFO
gen_name_szczep.egg-info/SOURCES.txt
gen_name_szczep.egg-info/dependency_links.txt
gen_name_szczep.egg-info/requires.txt
gen_name_szczep.egg-info/top_level.txt
gen_names_szczep/__init__.py
gen_names_szczep/get_name_szczep.py