Metadata-Version: 1.0
Name: gen-name-szczep
Version: 0.1.2
Summary: Super useful library
Home-page: http://github.com/treyhunner/names
Author: Szczepanek LTD
Author-email: szczepanek.pdm@gmail.com
License: UNKNOWN
Platform: UNKNOWN
